distributions/Binomialdistribution.py
distributions/Gaussiandistribution.py
distributions/Generaldistribution.py
distributions/__init__.py
distributions_josep-0.0.1.dist-info/licenses/LICENSE
distributions_josep-0.0.1.dist-info/METADATA
distributions_josep-0.0.1.dist-info/WHEEL
distributions_josep-0.0.1.dist-info/top_level.txt
distributions_josep-0.0.1.dist-info/RECORD
